py_js_runner/__init__.py
py_js_runner/errors.py
py_js_runner/js_runner.py
py_js_runner/npm.py
py_js_runner-1.0.0.dist-info/LICENSE
py_js_runner-1.0.0.dist-info/METADATA
py_js_runner-1.0.0.dist-info/WHEEL
py_js_runner-1.0.0.dist-info/top_level.txt
py_js_runner-1.0.0.dist-info/RECORD
