Metadata-Version: 2.1
Name: py-js-runner
Version: 1.0.0
Summary: Execute JavaScript Code From Python.
Home-page: UNKNOWN
Author: Yasir
Author-email: <yasirsadman@outlook.com>
License: UNKNOWN
Keywords: python,javascript,js,runjsfrompython
Platform: UNKNOWN
